Metadata-Version: 2.4
Name: bw2data
Version: 4.5.4
Summary: Tools for the management of inventory databases and impact assessment methods. Part of the Brightway LCA framework.
Author-email: Chris Mutel <cmutel@gmail.com>
Maintainer-email: Chris Mutel <cmutel@gmail.com>
Project-URL: source, https://github.com/brightway-lca/bw2data
Project-URL: homepage, https://github.com/brightway-lca/bw2data
Project-URL: tracker, https://github.com/brightway-lca/bw2data/issues
Classifier: Development Status :: 4 - Beta
Classifier: Programming Language :: Python
Classifier: Programming Language :: Python :: 3
Classifier: Programming Language :: Python :: 3.9
Classifier: Programming Language :: Python :: 3.10
Classifier: Programming Language :: Python :: 3.11
Classifier: Programming Language :: Python :: 3.12
Classifier: Natural Language :: English
Classifier: Operating System :: OS Independent
Classifier: Topic :: Scientific/Engineering
Requires-Python: >=3.9
License-File: LICENSE
Requires-Dist: blinker
Requires-Dist: bw2parameters
Requires-Dist: bw_processing>=0.9.5
Requires-Dist: deepdiff~=7.0.1
Requires-Dist: deprecated
Requires-Dist: fsspec
Requires-Dist: lxml
Requires-Dist: numpy<3
Requires-Dist: peewee>=3.9.4
Requires-Dist: pint
Requires-Dist: platformdirs
Requires-Dist: pydantic-settings
Requires-Dist: rapidfuzz; sys_platform != "emscripten"
Requires-Dist: scipy
Requires-Dist: snowflake-id~=1.0.2
Requires-Dist: stats_arrays
Requires-Dist: structlog
Requires-Dist: tqdm
Requires-Dist: typing_extensions
Requires-Dist: voluptuous
Requires-Dist: wrapt
Provides-Extra: testing
Requires-Dist: bw2data; extra == "testing"
Requires-Dist: bw2calc>=2.0.dev17; extra == "testing"
Requires-Dist: pytest; extra == "testing"
Requires-Dist: pytest-cov; extra == "testing"
Requires-Dist: python-coveralls; extra == "testing"
Provides-Extra: dev
Requires-Dist: build; extra == "dev"
Requires-Dist: pre-commit; extra == "dev"
Requires-Dist: pylint; extra == "dev"
Requires-Dist: pytest; extra == "dev"
Requires-Dist: pytest-cov; extra == "dev"
Requires-Dist: pytest-randomly; extra == "dev"
Requires-Dist: setuptools; extra == "dev"
Dynamic: license-file
